vietlm/__init__.py
vietlm/config/__init__.py
vietlm/config/dataset_arguments.py
vietlm/config/finetuning_arguments.py
vietlm/config/generate_arguments.py
vietlm/config/model_arguments.py
vietlm/inference/__init__.py
vietlm/inference/chat.py
vietlm/logging/__init__.py
vietlm/logging/logger.py
vietlm/models/__init__.py
vietlm/models/templates/__init__.py
vietlm/models/templates/template.py
vietlm/utils/__init__.py
vietlm/utils/args_utils.py
vietlm/utils/loader_utils.py
vietlm/utils/model_utils.py
vietlm-0.1.0.dist-info/LICENSE
vietlm-0.1.0.dist-info/METADATA
vietlm-0.1.0.dist-info/WHEEL
vietlm-0.1.0.dist-info/RECORD
